jolly_github_toolbelt/__init__.py
jolly_github_toolbelt/hooks/commit-msg
jolly_github_toolbelt/hooks/pre-commit
jolly_github_toolbelt/hooks/prepare-commit-msg
jolly_github_toolbelt-2.1.0.dist-info/entry_points.txt
jolly_github_toolbelt-2.1.0.dist-info/WHEEL
jolly_github_toolbelt-2.1.0.dist-info/METADATA
jolly_github_toolbelt-2.1.0.dist-info/RECORD
