Metadata-Version: 2.1
Name: jolly-github-toolbelt
Version: 2.1.0
Summary: A collection of tools around Git and GitHub to make developers' lives easier.
Home-page: https://jolly-good-toolbelt.github.io/jolly_github_toolbelt/
License: MIT
Author: Brad Brown
Author-email: brad@bradsbrown.com
Requires-Python: >=3.6,<4.0
Classifier: License :: OSI Approved :: MIT License
Classifier: Programming Language :: Python :: 3
Classifier: Programming Language :: Python :: 3.6
Classifier: Programming Language :: Python :: 3.7
Requires-Dist: github3.py (>=1.1.0,<2.0.0)
Requires-Dist: requests (>=2.10,<3.0)
Requires-Dist: tomlkit (>=0.5.3,<0.6.0)
Project-URL: Documentation, https://jolly-good-toolbelt.github.io/jolly_github_toolbelt/
Project-URL: Repository, https://github.com/jolly-good-toolbelt/jolly_github_toolbelt
